MANIFEST.in
README.md
setup.py
pechkin/__init__.py
pechkin/api.py
pechkin/errors.py
python_pechkin.egg-info/PKG-INFO
python_pechkin.egg-info/SOURCES.txt
python_pechkin.egg-info/dependency_links.txt
python_pechkin.egg-info/not-zip-safe
python_pechkin.egg-info/requires.txt
python_pechkin.egg-info/top_level.txt