Metadata-Version: 1.0
Name: python-pechkin
Version: 0.1.0
Summary: python api client for pechkin-mail.ru
Home-page: http://github.com/suvit/python-pechkin
Author: Victor Safronovich
Author-email: vsafronovich@gmail.com
License: MIT
Platform: UNKNOWN
Classifier: Development Status :: 5 - Production/Stable
Classifier: License :: OSI Approved :: MIT License
Classifier: Intended Audience :: Developers
Classifier: Operating System :: OS Independent
Classifier: Programming Language :: Python
Classifier: Programming Language :: Python :: 2.6
Classifier: Programming Language :: Python :: 2.7
Classifier: Environment :: Web Environment
Classifier: Topic :: Software Development
